MANIFEST.in
requirements.txt
setup.py
pyslth.egg-info/PKG-INFO
pyslth.egg-info/SOURCES.txt
pyslth.egg-info/dependency_links.txt
pyslth.egg-info/requires.txt
pyslth.egg-info/top_level.txt
slth/__init__.py
slth/components.py
slth/endpoints.py
slth/exceptions.py
slth/factory.py
slth/forms.py
slth/models.py
slth/notifications.py
slth/oauth.py
slth/permissions.py
slth/queryset.py
slth/roles.py
slth/serializer.py
slth/statistics.py
slth/tests.py
slth/urls.py
slth/utils.py
slth/views.py
slth/db/__init__.py
slth/db/models.py
slth/management/__init__.py
slth/management/commands/__init__.py
slth/management/commands/integration_test.py
slth/management/commands/sync.py
slth/migrations/0001_initial.py
slth/migrations/0002_email_role_pushsubscription_error.py
slth/migrations/0003_rename_photo_profile_alter_profile_options.py
slth/migrations/0004_alter_profile_photo.py
slth/migrations/0005_alter_profile_photo.py
slth/migrations/0006_user.py
slth/migrations/__init__.py
slth/selenium/__init__.py
slth/selenium/browser.py
slth/static/.DS_Store
slth/static/index.html
slth/static/css/.DS_Store
slth/static/css/fontawesome.min.css
slth/static/css/slth.css
slth/static/css/solid.min.css
slth/static/css/style.css
slth/static/css/fonts/.DS_Store
slth/static/css/fonts/fa-solid-900.woff2
slth/static/css/fonts/rawline-400.woff
slth/static/css/fonts/rawline-500i.woff
slth/static/css/fonts/rawline-700.woff
slth/static/images/logo.png
slth/static/images/logo.svg
slth/static/images/user.png
slth/static/images/user.svg
slth/static/js/default-passive-events.min.js
slth/static/js/echarts.min.js
slth/static/js/index.min.js
slth/static/js/ios-splash.min.js
slth/static/js/peerjs.min.js
slth/static/js/peerjs154.min.js
slth/static/js/qrcode.min.js
slth/static/js/react-trigger-change.js
slth/static/js/react.min.js
slth/static/js/slth.min.js
slth/static/js/vanilla-masker.js
slth/static/js/vanilla-masker.min.js
slth/templates/index.html
slth/templates/service-worker.js